B0tHe1Per_test_api
