Metadata-Version: 2.1
Name: B0tHe1Per-test-api
Version: 0.4
Summary: Test API for Bot Helper project
Home-page: https://github.com/serjbuda/B0tHe1Per.git
Author: Serj
Author-email: buda_serj@yahoo.com
